README.rst
setup.cfg
setup.py
modsecurity_exception_factory/__init__.py
modsecurity_exception_factory/modsecurity_audit_entry.py
modsecurity_exception_factory/modsecurity_audit_entry_message.py
modsecurity_exception_factory/modsecurity_exception_writer.py
modsecurity_exception_factory.egg-info/PKG-INFO
modsecurity_exception_factory.egg-info/SOURCES.txt
modsecurity_exception_factory.egg-info/dependency_links.txt
modsecurity_exception_factory.egg-info/entry_points.txt
modsecurity_exception_factory.egg-info/requires.txt
modsecurity_exception_factory.egg-info/top_level.txt
modsecurity_exception_factory/commands/__init__.py
modsecurity_exception_factory/commands/command_modsecurity_exception_factory.py
modsecurity_exception_factory/correlation/__init__.py
modsecurity_exception_factory/correlation/correlation.py
modsecurity_exception_factory/correlation/correlation_engine.py
modsecurity_exception_factory/correlation/correlation_merge_delegate.py
modsecurity_exception_factory/correlation/correlation_progress_listener_console.py
modsecurity_exception_factory/correlation/correlation_serializer_yaml.py
modsecurity_exception_factory/correlation/i_correlation_progress_listener.py
modsecurity_exception_factory/correlation/i_item_data_source.py
modsecurity_exception_factory/correlation/i_item_iterable.py
modsecurity_exception_factory/modsecurity_audit_data_source/__init__.py
modsecurity_exception_factory/modsecurity_audit_data_source/i_modsecurity_audit_data_source.py
modsecurity_exception_factory/modsecurity_audit_data_source/modsecurity_audit_data_source_sql.py
modsecurity_exception_factory/modsecurity_audit_data_source/modsecurity_audit_item_dict_iterable_sql.py
modsecurity_exception_factory/modsecurity_audit_data_source/sql_base.py
modsecurity_exception_factory/modsecurity_audit_data_source/sql_filter.py
modsecurity_exception_factory/modsecurity_audit_data_source/sql_filter_condition.py
modsecurity_exception_factory/modsecurity_audit_data_source/sql_modsecurity_audit_entry_message.py
modsecurity_exception_factory/modsecurity_audit_data_source/sql_session_maker_for_with_statement.py
modsecurity_exception_factory/modsecurity_audit_log_parser/__init__.py
modsecurity_exception_factory/modsecurity_audit_log_parser/i_modsecurity_audit_log_section_parser.py
