Metadata-Version: 1.1
Name: modsecurity-exception-factory
Version: 0.1.4
Summary: A tool that generates ModSecurity exception rules by automatically analyzing ModSecurity audit logs.
Home-page: https://github.com/shookalabs/modsecurity-exception-factory
Author: Younes JAAIDI
Author-email: yjaaidi@shookalabs.com
License: MIT
Platform: any
Classifier: Development Status :: 5 - Production/Stable
Classifier: License :: OSI Approved :: MIT License
Classifier: Programming Language :: Python :: 2
Classifier: Programming Language :: Python :: 3
Classifier: Topic :: Utilities
